soprano/__init__.py
soprano/cli.py
soprano/server.py
soprano/tts.py
soprano/webui.py
soprano/backends/base.py
soprano/backends/lmdeploy.py
soprano/backends/transformers.py
soprano/utils/auto_select.py
soprano/utils/streaming.py
soprano/utils/text_normalizer.py
soprano/utils/text_splitter.py
soprano/vocos/decoder.py
soprano/vocos/heads.py
soprano/vocos/models.py
soprano/vocos/modules.py
soprano/vocos/spectral_ops.py
soprano_tts-0.2.0.dist-info/licenses/LICENSE
soprano_tts-0.2.0.dist-info/METADATA
soprano_tts-0.2.0.dist-info/WHEEL
soprano_tts-0.2.0.dist-info/entry_points.txt
soprano_tts-0.2.0.dist-info/top_level.txt
soprano_tts-0.2.0.dist-info/RECORD
