Metadata-Version: 2.4
Name: soprano-tts
Version: 0.2.0
Summary: Soprano: Instant, Ultra‑Realistic Text‑to‑Speech
Author-email: ekwek1 <eugene.kwek.1@gmail.com>
License:                                  Apache License
Project-URL: Homepage, https://github.com/ekwek1/soprano
Project-URL: Issues, https://github.com/ekwek1/soprano/issues
Classifier: Programming Language :: Python :: 3
Classifier: Operating System :: OS Independent
Requires-Python: >=3.10
License-File: LICENSE
Requires-Dist: accelerate
Requires-Dist: fastapi
Requires-Dist: gradio
Requires-Dist: huggingface_hub
Requires-Dist: numpy
Requires-Dist: scipy
Requires-Dist: sounddevice
Requires-Dist: torch>=2.1.0
Requires-Dist: transformers>=4.51.0
Requires-Dist: unidecode
Requires-Dist: uvicorn
Requires-Dist: inflect
Provides-Extra: lmdeploy
Requires-Dist: lmdeploy; extra == "lmdeploy"
Dynamic: license-file
